{"is_source_file": false, "format": "", "description": "", "external_files": [], "external_methods": [], "published": [], "classes": [], "methods": [], "calls": [], "search-terms": [], "state": 2, "file_id": 35, "knowledge_revision": 78, "git_revision": "d817588e91a0e451b431ebba83282289df8bb429", "ctags": [], "hash": "6d0e3697ed489a31cdec9abd423fad64", "format-version": 4, "code-base-name": "career_navigator_backend", "filename": "career_navigator_backend/src/security/__init__.py", "revision_history": [{"78": "d817588e91a0e451b431ebba83282289df8bb429"}]}